canonical_interval.py
canonical_interval-0.1.0a2.dist-info/licenses/LICENSE
canonical_interval-0.1.0a2.dist-info/METADATA
canonical_interval-0.1.0a2.dist-info/WHEEL
canonical_interval-0.1.0a2.dist-info/top_level.txt
canonical_interval-0.1.0a2.dist-info/RECORD
