Metadata-Version: 2.4
Name: canonical-interval
Version: 0.1.0a2
Summary: Self-normalizing interval data structure that automatically maintains valid form with useful utility methods.
Author-email: Jifeng Wu <jifengwu2k@gmail.com>
License-Expression: MIT
Project-URL: Homepage, https://github.com/jifengwu2k/canonical-interval
Project-URL: Bug Tracker, https://github.com/jifengwu2k/canonical-interval/issues
Classifier: Programming Language :: Python :: 2
Classifier: Programming Language :: Python :: 3
Classifier: Operating System :: OS Independent
Requires-Python: >=2
License-File: LICENSE
Requires-Dist: enum34; python_version < "3.4"
Dynamic: license-file
